django_regiment/__init__.py
django_regiment/bulletlog/__init__.py
django_regiment/bulletlog/middleware.py
django_regiment/bulletlog/utils.py
django_regiment-1.0.0.dist-info/WHEEL
django_regiment-1.0.0.dist-info/METADATA
django_regiment-1.0.0.dist-info/RECORD
