Metadata-Version: 2.1
Name: django_regiment
Version: 1.0.0
Summary: django middleware for bulletlog
Home-page: https://www.regiment.tech/
Author: regiment.tech
Author-email: support@regiment.tech
Requires-Python: >=3.7
Classifier: License :: OSI Approved :: MIT License
Requires-Dist: django
Requires-Dist: requests
